vpk/__init__.py
vpk/cli.py
vpk-1.4.0.dist-info/LICENSE
vpk-1.4.0.dist-info/METADATA
vpk-1.4.0.dist-info/WHEEL
vpk-1.4.0.dist-info/entry_points.txt
vpk-1.4.0.dist-info/top_level.txt
vpk-1.4.0.dist-info/zip-safe
vpk-1.4.0.dist-info/RECORD
